kropotkin/__init__.py
kropotkin/_version.py
kropotkin-0.0.5.dist-info/METADATA
kropotkin-0.0.5.dist-info/WHEEL
kropotkin-0.0.5.dist-info/top_level.txt
kropotkin-0.0.5.dist-info/RECORD
