Metadata-Version: 2.1
Name: kropotkin
Version: 0.0.5
Summary: Hooks for stateless Django apps
Home-page: UNKNOWN
Author: Ross Fenning
Author-email: github@rossfenning.co.uk
License: UNKNOWN
Platform: UNKNOWN
Requires-Dist: msgpack
Requires-Dist: hhc
Provides-Extra: test
Requires-Dist: pytest ; extra == 'test'
Requires-Dist: hypothesis ; extra == 'test'
Requires-Dist: pytest-pikachu ; extra == 'test'
Requires-Dist: pytest-mypy ; extra == 'test'
